tests/__init__.py
tests/test_my_script.py
wordCounter/__init__.py
wordCounter/count.py
wordCounterByUstina-1.0.1.dist-info/LICENSE
wordCounterByUstina-1.0.1.dist-info/METADATA
wordCounterByUstina-1.0.1.dist-info/WHEEL
wordCounterByUstina-1.0.1.dist-info/top_level.txt
wordCounterByUstina-1.0.1.dist-info/RECORD
