Metadata-Version: 2.1
Name: wordCounterByUstina
Version: 1.0.1
Summary: Search for the number of words in a directory
Home-page: https://github.com/kuzminskayaaa/wordCcounter
Author: Kuzminskaya U.A.
Author-email: ustina.kuzminskaya@mail.ru
License: UNKNOWN
Platform: any
Requires-Python: >=3.7
